section/__init__.py
section/section.py
json_section-1.1.dist-info/LICENSE
json_section-1.1.dist-info/METADATA
json_section-1.1.dist-info/WHEEL
json_section-1.1.dist-info/entry_points.txt
json_section-1.1.dist-info/top_level.txt
json_section-1.1.dist-info/RECORD
