Metadata-Version: 2.1
Name: json-section
Version: 1.1
Summary: Tool used to return sections of JSON documents
Home-page: https://github.com/InfeCtlll3/json-section
Author: Carlos Armando
Author-email: contato.carmando@gmail.com
License: UNKNOWN
Keywords: json section cli
Platform: UNKNOWN
Classifier: Programming Language :: Python :: 3
Classifier: License :: OSI Approved :: MIT License
Classifier: Operating System :: OS Independent
Requires-Python: >=3.6
